{
  "dossier_id": "4192",
  "activities": [
    {
      "date": "09.08.1996",
      "type": "MEMORANDUM CONCERNANT LES AVIS DU CONSEIL D'ETAT (9.8.1996)",
      "description": "",
      "link": "https://wdocs-pub.chd.lu/docs/Dossiers_parlementaires/4192/20250515_Avis.pdf"
    },
    {
      "date": "12.08.1996",
      "type": "Déposé",
      "description": "",
      "link": "https://wdocs-pub.chd.lu/docs/Dossiers_parlementaires/4192/20250515_Depôt.pdf"
    },
    {
      "date": "07.11.1996",
      "type": "NOUVEAUX PLANS",
      "description": "",
      "link": "https://wdocs-pub.chd.lu/docs/Dossiers_parlementaires/4192/20250515_Avis_2.pdf"
    },
    {
      "date": "21.11.1996",
      "type": "Rapport de commission(s) : Commission des Travaux publics\n\nRapporteur(s) : Monsieur Jos Scheuer",
      "description": "Commission des Travaux publics",
      "link": "https://wdocs-pub.chd.lu/docs/Dossiers_parlementaires/4192/20250515_RapportCommission.pdf"
    },
    {
      "date": "05.12.1996",
      "type": "Premier vote constitutionnel (Vote Positif)\n\nUne demande de dispense du second vote a été introduite",
      "description": ""
    },
    {
      "date": "20.12.1996",
      "type": "Dispense du second vote constitutionnel par le Conseil d'Etat (20-12-1996)\n\nEvacué par dispense du second vote (20-12-1996)\n                \n              \n            \n            \n              Bouton graphique servant à afficher ou cacher tous les éléments de la liste qui précède\n              \n                  Show more\n              \n              \n                  Voir moins",
      "description": "Conseil d'État",
      "link": "https://wdocs-pub.chd.lu/docs/Dossiers_parlementaires/4192/20250513_AccordDispenseSecondVote.pdf"
    },
    {
      "date": "31.12.1997",
      "type": "Publié au Mémorial A n°3 en page 27",
      "description": ""
    }
  ]
}
