{
  "dossier_id": "4401",
  "activities": [
    {
      "date": "26.01.1998",
      "type": "Déposé",
      "description": "",
      "link": "https://wdocs-pub.chd.lu/docs/Dossiers_parlementaires/4401/20250514_Depôt.pdf"
    },
    {
      "date": "26.01.1998",
      "type": "Renvoyé en commission(s) : Commission des Institutions et de la Révision constitutionnelle",
      "description": "Commission des Institutions et de la Révision constitutionnelle"
    },
    {
      "date": "10.11.1998",
      "type": "4424/1\nProposition de loi sur le remboursement partiel des frais des campagnes électorales aux partis politiques engagés dans les élections à la Chambre des Députés et au Parlement européen\n\n\nAvis du Conseil d'Etat (10.11.1998)\n                \n              \n            \n            \n              Bouton graphique servant à afficher ou cacher tous les éléments de la liste qui précède\n              \n                  Show more\n              \n              \n                  Voir moins",
      "description": "Conseil d'État",
      "link": "https://wdocs-pub.chd.lu/docs/Dossiers_parlementaires/4401/20250514_Avis.pdf"
    },
    {
      "date": "13.10.2009",
      "type": "Retrait du rôle des affaires de la Chambre des Députés\n1) Dépêche du Président de la Chambre des Députés au Premier Ministre, Ministre d'Etat (13.10.2009)\n2) Liste des propositions de loi à retirer du rôle des affaires de la Chambre des Députés\n                \n              \n            \n            \n              Bouton graphique servant à afficher ou cacher tous les éléments de la liste qui précède\n              \n                  Show more\n              \n              \n                  Voir moins",
      "description": "Chambre des Députés",
      "link": "https://wdocs-pub.chd.lu/docs/Dossiers_parlementaires/4401/20250515_RetraitRôleDesAffaires.pdf"
    }
  ]
}
