{
  "dossier_id": "4850",
  "activities": [
    {
      "date": "13.06.2002",
      "type": "Déposé",
      "description": "Commission des Media et des Communications",
      "link": "https://wdocs-pub.chd.lu/docs/Debats/4850/20250514/20250514_Depôt.pdf"
    },
    {
      "date": "13.06.2002",
      "type": "Vidé en séance publique n°52",
      "description": ""
    },
    {
      "date": "13.06.2002",
      "type": "Débat d'orientation sur le bilan de la loi du 27 juillet 1991 sur les médias électroniques - Rapporteur : M. Laurent Mosar\n                \n              \n            \n            \n              Bouton graphique servant à afficher ou cacher tous les éléments de la liste qui précède\n              \n                  Show more\n              \n              \n                  Voir moins",
      "description": "",
      "link": "https://wdocs-pub.chd.lu/docs/archive/04/04/704772_pdf"
    }
  ]
}
