{
  "dossier_id": "4932",
  "activities": [
    {
      "date": "28.03.2002",
      "type": "Déposé",
      "description": "Lydie Polfer",
      "link": "https://wdocs-pub.chd.lu/docs/Dossiers_parlementaires/4932/20250515_Depôt.pdf"
    },
    {
      "date": "16.04.2002",
      "type": "Avis du Conseil d'Etat (16.4.2002)",
      "description": "Conseil d'État",
      "link": "https://wdocs-pub.chd.lu/docs/Dossiers_parlementaires/4932/20250514_Avis.pdf"
    },
    {
      "date": "25.04.2002",
      "type": "Avis de la Conférence des Présidents (25-04-2002)",
      "description": "Conférence des Présidents",
      "link": "https://wdocs-pub.chd.lu/docs/Dossiers_parlementaires/4932/20250514_Avis_2.pdf"
    },
    {
      "date": "13.03.2017",
      "type": "Retrait du rôle des affaires\n- Dépêche du Ministre aux Relations avec le Parlement au Président de la Chambre des Députés (10.3.2017)\n                \n              \n            \n            \n              Bouton graphique servant à afficher ou cacher tous les éléments de la liste qui précède\n              \n                  Show more\n              \n              \n                  Voir moins",
      "description": "",
      "link": "https://wdocs-pub.chd.lu/docs/Dossiers_parlementaires/4932/20250514_RetraitRôleDesAffaires.pdf"
    }
  ]
}
