{
  "dossier_id": "4967",
  "activities": [
    {
      "date": "06.06.2002",
      "type": "Déposé",
      "description": "Lydie Polfer",
      "link": "https://wdocs-pub.chd.lu/docs/Dossiers_parlementaires/4967/20250515_Depot.pdf"
    },
    {
      "date": "26.11.2002",
      "type": "Avis de du Conseil d'Etat (26.11.2002)",
      "description": "Conseil d'État",
      "link": "https://wdocs-pub.chd.lu/docs/Dossiers_parlementaires/4967/20250513_Avis.pdf"
    },
    {
      "date": "06.02.2003",
      "type": "Rapport de commission(s) : Commission des Media et des Communications\n\nRapporteur(s) : Monsieur Jean-Marie Halsdorf",
      "description": "Jean-Marie Halsdorf\n                      Commission des Media et des Communications",
      "link": "https://wdocs-pub.chd.lu/docs/Dossiers_parlementaires/4967/20250513_RapportCommission.pdf"
    },
    {
      "date": "11.02.2003",
      "type": "Premier vote constitutionnel (Vote Positif)\n\nUne demande de dispense du second vote a été introduite",
      "description": ""
    },
    {
      "date": "11.02.2003",
      "type": "Projet de loi portant approbation- de la Constitution de l'Union internationale des télécommunications et de son annexe ainsi de la Convention  de l'Union internationale des télécommunications et de son annexe, signées à Genève le 22 décembre 1992, telles qu'amendées par les Conférences de plénipotentiaires de l'Union internationale des télécommunications à Kyoto, le 14 octobre 1994 et à Minneapolis, le 6 novembre 1998 ;\n - des résolutions, décisions et recommandations faisant partie des Actes finals de la Conférence de plénipotentiaires additionnelle de l'Union internationale des télécommunications (Genève 1992) et des Conférences de plénipotentiaires de l'Union internationale des télécommunications de Kyoto (1994) et de Minneapolis (1998) - Rapporteur : M. Jean-Marie Halsdorf\n                \n              \n            \n            \n              Bouton graphique servant à afficher ou cacher tous les éléments de la liste qui précède\n              \n                  Show more\n              \n              \n                  Voir moins",
      "description": "",
      "link": "https://www.chd.lu/en/seance/1047"
    },
    {
      "date": "25.02.2003",
      "type": "Dispense du second vote constitutionnel par le Conseil d'Etat (25-02-2003)\n\nEvacué par dispense du second vote (25-02-2003)\n                \n              \n            \n            \n              Bouton graphique servant à afficher ou cacher tous les éléments de la liste qui précède\n              \n                  Show more\n              \n              \n                  Voir moins",
      "description": "Conseil d'État",
      "link": "https://wdocs-pub.chd.lu/docs/Dossiers_parlementaires/4967/20250513_AccordDispenseSecondVote.pdf"
    },
    {
      "date": "31.12.2003",
      "type": "Publié au Mémorial A n°47 en page 727",
      "description": ""
    }
  ]
}
