{
  "dossier_id": "5001",
  "activities": [
    {
      "date": "30.07.2002",
      "type": "Déposé",
      "description": "",
      "link": "https://wdocs-pub.chd.lu/docs/Dossiers_parlementaires/5001/20250514_Depôt.pdf"
    },
    {
      "date": "06.08.2002",
      "type": "1) Avis de la Chambre de Commerce (6.8.2002)\n2) Avis de la Chambre des Employés privés (20.8.2002)",
      "description": "",
      "link": "https://wdocs-pub.chd.lu/docs/Dossiers_parlementaires/5001/20250513_Avis_2.pdf"
    },
    {
      "date": "26.08.2002",
      "type": "Avis de la Chambre des Métiers (26.8.2002)",
      "description": "",
      "link": "https://wdocs-pub.chd.lu/docs/Dossiers_parlementaires/5001/20250513_Avis_3.pdf"
    },
    {
      "date": "24.09.2002",
      "type": "Avis du Conseil d'Etat (24.9.2002)",
      "description": "Conseil d'État",
      "link": "https://wdocs-pub.chd.lu/docs/Dossiers_parlementaires/5001/20250513_Avis_4.pdf"
    },
    {
      "date": "02.10.2002",
      "type": "Avis de la Chambre de Travail (2.10.2002)",
      "description": "",
      "link": "https://wdocs-pub.chd.lu/docs/Dossiers_parlementaires/5001/20250513_Avis_6.pdf"
    },
    {
      "date": "18.02.2003",
      "type": "1) Dépêche du Ministre aux Relations avec le Parlement au Président de la Chambre des Députés (18.2.2003)\n2) Texte du projet de règlement grand-ducal modifié\n3) Prise de position du Ministre du Travail et de l'Emploi (10.2.2003)\n                \n              \n            \n            \n              Bouton graphique servant à afficher ou cacher tous les éléments de la liste qui précède\n              \n                  Show more\n              \n              \n                  Voir moins",
      "description": "Gouvernement",
      "link": "https://wdocs-pub.chd.lu/docs/Dossiers_parlementaires/5001/20250513_Avis_5.pdf"
    },
    {
      "date": "27.02.2003",
      "type": "Avis de la Conférence des Présidents (27-02-2003)",
      "description": "Conférence des Présidents",
      "link": "https://wdocs-pub.chd.lu/docs/Dossiers_parlementaires/5001/20250513_Avis.pdf"
    },
    {
      "date": "31.12.2003",
      "type": "Publié au Mémorial A n°54 en page 916",
      "description": ""
    }
  ]
}
