{
  "dossier_id": "5537",
  "activities": [
    {
      "date": "01.02.2006",
      "type": "Déposé",
      "description": "",
      "link": "https://wdocs-pub.chd.lu/docs/Dossiers_parlementaires/5537/20250515_Depôt.pdf"
    },
    {
      "date": "11.05.2006",
      "type": "- Désignation d'un Rapporteur\n- Examen du projet de loi et de l'avis du Conseil d'Etat",
      "description": "Commission de l'Education nationale et de la Formation professionnelle"
    },
    {
      "date": "12.06.2006",
      "type": "Avis du Comité Olympique et Sportif Luxembourgeois (12.6.2006)",
      "description": "",
      "link": "https://wdocs-pub.chd.lu/docs/Dossiers_parlementaires/5537/20250515_Avis_2.pdf"
    },
    {
      "date": "28.06.2006",
      "type": "Amendements gouvernementaux\n1) Dépêche de la Secrétaire d'Etat aux Relations avec le Parlement au Président de la Chambre des Députés (28.6.2006)\n2) Texte des amendements avec commentaires\n3) Texte amendé du projet de loi\n                \n              \n            \n            \n              Bouton graphique servant à afficher ou cacher tous les éléments de la liste qui précède\n              \n                  Show more\n              \n              \n                  Voir moins",
      "description": "Gouvernement",
      "link": "https://wdocs-pub.chd.lu/docs/Dossiers_parlementaires/5537/20250515_AmendementGouvernemental.pdf"
    },
    {
      "date": "27.09.2006",
      "type": "- Rapporteur : Monsieur Alex Bodry\n\n- Examen du projet de loi et de l'avis du Conseil d'Etat",
      "description": "Commission de l'Economie, de l'Energie, des Postes et des Sports"
    },
    {
      "date": "10.10.2006",
      "type": "Avis du Conseil d'Etat (10.10.2006)",
      "description": "Conseil d'État",
      "link": "https://wdocs-pub.chd.lu/docs/Dossiers_parlementaires/5537/20250515_Avis.pdf"
    },
    {
      "date": "17.10.2006",
      "type": "Rapport de commission(s) : Commission de l'Economie, de l'Energie, des Postes et des Sports\n\nRapporteur(s) : Monsieur Alex Bodry\n                \n              \n            \n            \n              Bouton graphique servant à afficher ou cacher tous les éléments de la liste qui précède\n              \n                  Show more\n              \n              \n                  Voir moins",
      "description": "Commission de l'Economie, de l'Energie, des Postes et des Sports",
      "link": "https://wdocs-pub.chd.lu/docs/Dossiers_parlementaires/5537/20250515_RapportCommission.pdf"
    },
    {
      "date": "17.10.2006",
      "type": "",
      "description": "Commission de l'Economie, de l'Energie, des Postes et des Sports"
    },
    {
      "date": "24.10.2006",
      "type": "Premier vote constitutionnel (Vote Positif)\n\nUne demande de dispense du second vote a été introduite",
      "description": ""
    },
    {
      "date": "14.11.2006",
      "type": "Dispense du second vote constitutionnel par le Conseil d'Etat (14-11-2006)\n\nEvacué par dispense du second vote (14-11-2006)\n                \n              \n            \n            \n              Bouton graphique servant à afficher ou cacher tous les éléments de la liste qui précède\n              \n                  Show more\n              \n              \n                  Voir moins",
      "description": "Conseil d'État",
      "link": "https://wdocs-pub.chd.lu/docs/Dossiers_parlementaires/5537/20250515_AccordDispenseSecondVote.pdf"
    },
    {
      "date": "31.12.2006",
      "type": "Publié au Mémorial A n°206 en page 3490",
      "description": ""
    }
  ]
}
