{
  "dossier_id": "6088",
  "activities": [
    {
      "date": "18.11.2009",
      "type": "Déposé",
      "description": "Commission des Pétitions",
      "link": "https://wdocs-pub.chd.lu/docs/Debats/6088/20250514/20250515_Depôt.pdf"
    },
    {
      "date": "18.11.2009",
      "type": "Renvoyé en commission(s) : Commission des Pétitions\n\nRapporteur(s) : Monsieur Camille Gira",
      "description": "Commission des Pétitions\n                      Camille Gira"
    },
    {
      "date": "06.01.2010",
      "type": "- Désignation d'un rapporteur\n- Préparation du débat d'orientation",
      "description": "Commission des Pétitions"
    },
    {
      "date": "20.01.2010",
      "type": "- Rapporteur : Monsieur Camille Gira\n\n- Echange de vues avec des représentants gouvernementaux au sujet du recrutement de personnel dans la fonction publique\n                \n              \n            \n            \n              Bouton graphique servant à afficher ou cacher tous les éléments de la liste qui précède\n              \n                  Show more\n              \n              \n                  Voir moins",
      "description": "Commission de la Fonction publique et de la Simplification administrative\n                      Commission des Pétitions",
      "link": "https://wdocs-pub.chd.lu/docs/exped/082/898/088917.pdf"
    },
    {
      "date": "28.01.2010",
      "type": "- Rapporteur : Monsieur Camille Gira\n- Suite des discussions de la réunion du 20 janvier 2010",
      "description": "Commission des Pétitions",
      "link": "https://wdocs-pub.chd.lu/docs/exped/070/879/086798.pdf"
    },
    {
      "date": "04.02.2010",
      "type": "- Rapporteur : Monsieur Camille Gira\n- Entrevue avec des représentants du SYVICOL",
      "description": "Commission des Pétitions",
      "link": "https://wdocs-pub.chd.lu/docs/exped/071/870/087609.pdf"
    },
    {
      "date": "22.02.2010",
      "type": "- Rapporteur : Monsieur Camille Gira\n- Echange de vues avec Monsieur le Secrétaire général de la Chambre des Députés sur une administration publique efficace\n                \n              \n            \n            \n              Bouton graphique servant à afficher ou cacher tous les éléments de la liste qui précède\n              \n                  Show more\n              \n              \n                  Voir moins",
      "description": "Commission des Pétitions",
      "link": "https://wdocs-pub.chd.lu/docs/exped/071/869/087608.pdf"
    },
    {
      "date": "18.03.2010",
      "type": "- Rapporteur : Monsieur Camille Gira\n- Echange de vues avec Monsieur le Ministre de l'Intérieur et à la Grande Région\n                \n              \n            \n            \n              Bouton graphique servant à afficher ou cacher tous les éléments de la liste qui précède\n              \n                  Show more\n              \n              \n                  Voir moins",
      "description": "Commission des Pétitions",
      "link": "https://wdocs-pub.chd.lu/docs/exped/084/847/088436.pdf"
    },
    {
      "date": "20.04.2010",
      "type": "- Rapporteur : Monsieur Camille Gira\n- Conclusions de la Commission, en vue de la rédaction du projet de rapport",
      "description": "Commission des Pétitions",
      "link": "https://wdocs-pub.chd.lu/docs/exped/086/888/088857.pdf"
    },
    {
      "date": "03.05.2010",
      "type": "- Rapporteur : Monsieur Camille Gira\n- Présentation et adoption d'un projet de rapport",
      "description": "Commission des Pétitions",
      "link": "https://wdocs-pub.chd.lu/docs/exped/098/852/089571.pdf"
    },
    {
      "date": "02.06.2010",
      "type": "- Rapporteur : Monsieur Camille Gira\n- Examen de projets de motion",
      "description": "Commission des Pétitions",
      "link": "https://wdocs-pub.chd.lu/docs/exped/012/909/091018.pdf"
    },
    {
      "date": "07.07.2010",
      "type": "Vidé en séance publique n°41",
      "description": ""
    },
    {
      "date": "07.07.2010",
      "type": "Débat d'orientation sur le rapport d'activité du Médiateur (2008-2009)",
      "description": "",
      "link": "https://www.chd.lu/en/seance/1650?sequenceId=7068"
    }
  ]
}
