{
  "dossier_id": "6174",
  "activities": [
    {
      "date": "13.08.2010",
      "type": "Déposé",
      "description": "",
      "link": "https://wdocs-pub.chd.lu/docs/Dossiers_parlementaires/6174/20250515_Depôt.pdf"
    },
    {
      "date": "17.09.2010",
      "type": "Avis de la Chambre de Commerce (6.9.2010)",
      "description": "",
      "link": "https://wdocs-pub.chd.lu/docs/Dossiers_parlementaires/6174/20250515_Avis_2.pdf"
    },
    {
      "date": "13.10.2010",
      "type": "Avis du Conseil d'Etat (12.10.2010)",
      "description": "Conseil d'État",
      "link": "https://wdocs-pub.chd.lu/docs/Dossiers_parlementaires/6174/20250515_Avis_4.pdf"
    },
    {
      "date": "21.10.2010",
      "type": "Prise de position du Gouvernement\n1) Dépêche de la Ministre aux Relations avec le Parlement au Président de la Chambre des Députés (20.10.2010)\n2) Texte coordonné\n                \n              \n            \n            \n              Bouton graphique servant à afficher ou cacher tous les éléments de la liste qui précède\n              \n                  Show more\n              \n              \n                  Voir moins",
      "description": "Gouvernement",
      "link": "https://wdocs-pub.chd.lu/docs/Dossiers_parlementaires/6174/20250515_PositionGouvernement.pdf"
    },
    {
      "date": "18.11.2010",
      "type": "Avis de la Conférence des Présidents (18-11-2010)",
      "description": "Conférence des Présidents",
      "link": "https://wdocs-pub.chd.lu/docs/Dossiers_parlementaires/6174/20250515_Avis.pdf"
    },
    {
      "date": "18.11.2010",
      "type": "",
      "description": "Conférence des Présidents"
    },
    {
      "date": "29.11.2010",
      "type": "Publié au Mémorial A n°210 en page 3454",
      "description": ""
    },
    {
      "date": "01.12.2010",
      "type": "Avis de la Chambre des Métiers (8.11.2010)",
      "description": "",
      "link": "https://wdocs-pub.chd.lu/docs/Dossiers_parlementaires/6174/20250515_Avis_3.pdf"
    }
  ]
}
