{
  "dossier_id": "6695",
  "activities": [
    {
      "date": "10.06.2014",
      "type": "Déposé",
      "description": "François Bausch",
      "link": "https://wdocs-pub.chd.lu/docs/Dossiers_parlementaires/6695/20250514_Depôt.pdf"
    },
    {
      "date": "10.06.2014",
      "type": "Commission pressentie",
      "description": "Commission du Développement durable"
    },
    {
      "date": "24.06.2014",
      "type": "Avis de la Chambre des Métiers (13.6.2014)",
      "description": "",
      "link": "https://wdocs-pub.chd.lu/docs/Dossiers_parlementaires/6695/20250514_Avis.pdf"
    },
    {
      "date": "25.06.2014",
      "type": "Avis du Conseil d'Etat (24.6.2014)",
      "description": "Conseil d'État",
      "link": "https://wdocs-pub.chd.lu/docs/Dossiers_parlementaires/6695/20250514_Avis_2.pdf"
    },
    {
      "date": "26.06.2014",
      "type": "Renvoyé en commission(s) : Commission du Développement durable\n\nDate prévisionnelle du rapport de commission : 12-03-2015\n                \n              \n            \n            \n              Bouton graphique servant à afficher ou cacher tous les éléments de la liste qui précède\n              \n                  Show more\n              \n              \n                  Voir moins",
      "description": "Commission du Développement durable"
    },
    {
      "date": "03.12.2014",
      "type": "- Désignation d'un rapporteur\n- Présentation du projet de loi\n- Examen de l'avis du Conseil d'Etat",
      "description": "Commission du Développement durable",
      "link": "https://wdocs-pub.chd.lu/docs/exped/186/393/138952.pdf"
    },
    {
      "date": "10.12.2014",
      "type": "Changement d'intitulé\n\nAncien intitulé : Projet de loi déterminant le régime des sanctions applicables en cas de violation des dispositions du règlement (UE) n° 181/2011 du Parlement européen et du Conseil du 16 février 2011 concernant les droits des passagers dans le transport par autobus et autocar ; modifiant la loi du 8 avril 2011 portant introduction d'un Code de la consommation ; modifiant la loi du 29 juin 2004 portant sur les transports publics\n\nNouvel intitulé : Projet de loi déterminant le régime des sanctions applicables en cas de violation des dispositions du règlement (UE) n° 181/2011 du Parlement européen et du Conseil du 16\nfévrier 2011 concernant les droits des passagers dans le transport par autobus et autocar et\nmodifiant le règlement (CE) n° 2006/2004, et modifiant\n1) les articles L. 311-5 et L. 311-6 du Code de la consommation,\n2) l'article 7bis de la loi modifiée du 29 juin 2004 sur les transports publics\n                \n              \n            \n            \n              Bouton graphique servant à afficher ou cacher tous les éléments de la liste qui précède\n              \n                  Show more\n              \n              \n                  Voir moins",
      "description": ""
    },
    {
      "date": "10.12.2014",
      "type": "Nomination de rapporteur(s)\n\nRapporteur(s) : Madame Josée Lorsché",
      "description": "Josée Lorsché\n                      Commission du Développement durable"
    },
    {
      "date": "07.01.2015",
      "type": "Amendements adoptés par la/les commission(s) : Commission du Développement durable",
      "description": "Commission du Développement durable",
      "link": "https://wdocs-pub.chd.lu/docs/Dossiers_parlementaires/6695/20250514_AmendementParlementaire.pdf"
    },
    {
      "date": "07.01.2015",
      "type": "- Rapporteur: Madame Josée Lorsché\n- Présentation et adoption d'une série d'amendements parlementaires",
      "description": "Commission du Développement durable",
      "link": "https://wdocs-pub.chd.lu/docs/exped/196/345/139454.pdf"
    },
    {
      "date": "25.02.2015",
      "type": "Avis complémentaire du Conseil d'État (24.2.2015)",
      "description": "Conseil d'État",
      "link": "https://wdocs-pub.chd.lu/docs/Dossiers_parlementaires/6695/20250514_Avis_3.pdf"
    },
    {
      "date": "03.03.2015",
      "type": "- Rapporteur: Madame Josée Lorsché\n- Examen de l'avis complémentaire du Conseil d'Etat",
      "description": "Commission du Développement durable",
      "link": "https://wdocs-pub.chd.lu/docs/exped/127/412/142161.pdf"
    },
    {
      "date": "12.03.2015",
      "type": "Rapport de commission(s) : Commission du Développement durable\n\nRapporteur(s) : Madame Josée Lorsché",
      "description": "Commission du Développement durable\n                      Josée Lorsché",
      "link": "https://wdocs-pub.chd.lu/docs/Dossiers_parlementaires/6695/20250514_RapportCommission.pdf"
    },
    {
      "date": "12.03.2015",
      "type": "- Rapporteur: Madame Josée Lorsché\n- Présentation et adoption d'un projet de rapport",
      "description": "Commission du Développement durable",
      "link": "https://wdocs-pub.chd.lu/docs/exped/127/413/142162.pdf"
    },
    {
      "date": "17.03.2015",
      "type": "Premier vote constitutionnel (Vote Positif)\n\nEn séance publique n°24\n\nUne demande de dispense du second vote a été introduite\n                \n              \n            \n            \n              Bouton graphique servant à afficher ou cacher tous les éléments de la liste qui précède\n              \n                  Show more\n              \n              \n                  Voir moins",
      "description": "",
      "link": "https://wdocs-pub.chd.lu/docs/Dossiers_parlementaires/6695/20250514_BulletinVote.pdf"
    },
    {
      "date": "17.03.2015",
      "type": "6695 - Projet de loi déterminant le régime des sanctions applicables en cas de violation des dispositions du règlement (UE) n° 181/2011 du Parlement européen et du Conseil du 16\nfévrier 2011 concernant les droits des passagers dans le transport par autobus et autocar et\nmodifiant le règlement (CE) n° 2006/2004, et modifiant\n1) les articles L. 311-5 et L. 311-6 du Code de la consommation,\n2) l'article 7bis de la loi modifiée du 29 juin 2004 sur les transports publics\n - Rapportrice : Madame Josée Lorsché\n                \n              \n            \n            \n              Bouton graphique servant à afficher ou cacher tous les éléments de la liste qui précède\n              \n                  Show more\n              \n              \n                  Voir moins",
      "description": "",
      "link": "https://www.chd.lu/en/seance/1974?sequenceId=238664"
    },
    {
      "date": "26.03.2015",
      "type": "Dispense du second vote constitutionnel par le Conseil d'Etat (26-03-2015)\n\nEvacué par dispense du second vote (26-03-2015)\n                \n              \n            \n            \n              Bouton graphique servant à afficher ou cacher tous les éléments de la liste qui précède\n              \n                  Show more\n              \n              \n                  Voir moins",
      "description": "Conseil d'État",
      "link": "https://wdocs-pub.chd.lu/docs/Dossiers_parlementaires/6695/20250514_AccordDispenseSecondVote.pdf"
    },
    {
      "date": "04.05.2015",
      "type": "Publié au Mémorial A n°82 en page 1500",
      "description": ""
    }
  ]
}
