{
  "dossier_id": "6795",
  "activities": [
    {
      "date": "20.03.2015",
      "type": "Déposé",
      "description": "",
      "link": "https://wdocs-pub.chd.lu/docs/Dossiers_parlementaires/6795/20250514_Depôt.pdf"
    },
    {
      "date": "20.03.2015",
      "type": "Commission pressentie",
      "description": "Commission de l'Economie"
    },
    {
      "date": "23.04.2015",
      "type": "Renvoyé en commission(s) : Commission de l'Economie",
      "description": "Commission de l'Economie"
    },
    {
      "date": "24.06.2015",
      "type": "Avis de la Chambre de Commerce (18.6.2015)",
      "description": "",
      "link": "https://wdocs-pub.chd.lu/docs/Dossiers_parlementaires/6795/20250514_Avis_3.pdf"
    },
    {
      "date": "24.09.2015",
      "type": "Avis de la Chambre des Métiers (18.9.2015)",
      "description": "",
      "link": "https://wdocs-pub.chd.lu/docs/Dossiers_parlementaires/6795/20250514_Avis.pdf"
    },
    {
      "date": "21.10.2015",
      "type": "Avis du Conseil d'État (20.10.2015)",
      "description": "Conseil d'État",
      "link": "https://wdocs-pub.chd.lu/docs/Dossiers_parlementaires/6795/20250514_Avis_4.pdf"
    },
    {
      "date": "19.11.2015",
      "type": "Avis de la Confédération Luxembourgeoise du Commerce et de la Chambre Immobilière\n- Dépêche du Vice-Président de la Confédération Luxembourgeoise du Commerce et du Président de la Chambre Immobilière au Ministre de l'Economie (11.11.2015)\n                \n              \n            \n            \n              Bouton graphique servant à afficher ou cacher tous les éléments de la liste qui précède\n              \n                  Show more\n              \n              \n                  Voir moins",
      "description": "",
      "link": "https://wdocs-pub.chd.lu/docs/Dossiers_parlementaires/6795/20250513_Avis.pdf"
    },
    {
      "date": "04.12.2015",
      "type": "Avis complémentaire de la Chambre des Métiers \n1) Dépêche du Président de la Chambre des Métiers au Ministre de l'Economie (27.11.2015)\n2) Avis de la Chambre des Métiers (18.9.2015)\n                \n              \n            \n            \n              Bouton graphique servant à afficher ou cacher tous les éléments de la liste qui précède\n              \n                  Show more\n              \n              \n                  Voir moins",
      "description": "",
      "link": "https://wdocs-pub.chd.lu/docs/Dossiers_parlementaires/6795/20250514_Avis_5.pdf"
    },
    {
      "date": "23.12.2015",
      "type": "Avis du Conseil de la concurrence (17.12.2015)",
      "description": "",
      "link": "https://wdocs-pub.chd.lu/docs/Dossiers_parlementaires/6795/20250514_Avis_2.pdf"
    },
    {
      "date": "13.12.2018",
      "type": "Renvoyé en commission(s) : Commission de l'Economie, de la Protection des consommateurs et de l'Espace",
      "description": "Commission de l'Economie, de la Protection des consommateurs et de l'Espace"
    },
    {
      "date": "24.01.2019",
      "type": "Renvoyé en commission(s) : Commission des Classes moyennes et du Tourisme",
      "description": "Commission des Classes moyennes et du Tourisme"
    },
    {
      "date": "17.12.2021",
      "type": "Arrêté Grand-Ducal de retrait du rôle des affaires de la Chambre des Députés (15.12.2021)",
      "description": "Lex Delles",
      "link": "https://wdocs-pub.chd.lu/docs/Dossiers_parlementaires/6795/20250513_RetraitRôleDesAffaires.pdf"
    }
  ]
}
