{
  "dossier_id": "7081",
  "activities": [
    {
      "date": "24.10.2016",
      "type": "Déposé",
      "description": "",
      "link": "https://wdocs-pub.chd.lu/docs/Dossiers_parlementaires/7081/20250514_Depôt.pdf"
    },
    {
      "date": "24.10.2016",
      "type": "Commission pressentie",
      "description": "Commission des Affaires étrangères et européennes, de la Défense, de la Coopération et de l'Immigration"
    },
    {
      "date": "10.11.2016",
      "type": "Renvoyé en commission(s) : Commission des Affaires étrangères et européennes, de la Défense, de la Coopération et de l'Immigration\n                \n              \n            \n            \n              Bouton graphique servant à afficher ou cacher tous les éléments de la liste qui précède\n              \n                  Show more\n              \n              \n                  Voir moins",
      "description": "Commission des Affaires étrangères et européennes, de la Défense, de la Coopération et de l'Immigration"
    },
    {
      "date": "14.12.2016",
      "type": "Avis du Conseil d'État (13.12.2016)",
      "description": "Conseil d'État",
      "link": "https://wdocs-pub.chd.lu/docs/Dossiers_parlementaires/7081/20250513_Avis.pdf"
    },
    {
      "date": "16.12.2016",
      "type": "- Adoption d'un projet d'avis à l'intention de la Conférence des Présidents",
      "description": "Commission des Affaires étrangères et européennes, de la Défense, de la Coopération et de l'Immigration",
      "link": "https://wdocs-pub.chd.lu/docs/exped/0000/197/1979.pdf"
    },
    {
      "date": "20.12.2016",
      "type": "Prise de position du Gouvernement\n1) Dépêche du Ministre aux Relations avec le Parlement au Président de la Chambre des Députés (20.12.2016)\n2) Dépêche du Ministre de la Défense au Premier Ministre, Ministre d'Etat (14.12.2016)\n3) Texte coordonné\n                \n              \n            \n            \n              Bouton graphique servant à afficher ou cacher tous les éléments de la liste qui précède\n              \n                  Show more\n              \n              \n                  Voir moins",
      "description": "Gouvernement",
      "link": "https://wdocs-pub.chd.lu/docs/Dossiers_parlementaires/7081/20250514_PositionGouvernement.pdf"
    },
    {
      "date": "20.12.2016",
      "type": "Avis de la Conférence des Présidents (20-12-2016)",
      "description": "Conférence des Présidents",
      "link": "https://wdocs-pub.chd.lu/docs/Dossiers_parlementaires/7081/20250513_Avis_2.pdf"
    },
    {
      "date": "27.12.2016",
      "type": "Publié au Mémorial A n°284 en page 5966",
      "description": ""
    }
  ]
}
