{
  "dossier_id": "7260",
  "activities": [
    {
      "date": "13.03.2018",
      "type": "Déposé",
      "description": "",
      "link": "https://wdocs-pub.chd.lu/docs/Dossiers_parlementaires/7260/20250515_Depot.pdf"
    },
    {
      "date": "13.03.2018",
      "type": "Commission pressentie",
      "description": "Commission des Affaires étrangères et européennes, de la Défense, de la Coopération et de l'Immigration"
    },
    {
      "date": "15.03.2018",
      "type": "Renvoyé en commission(s) : Commission des Affaires étrangères et européennes, de la Défense, de la Coopération et de l'Immigration\n\nDate prévisionnelle du rapport de commission : 11-06-2018\n                \n              \n            \n            \n              Bouton graphique servant à afficher ou cacher tous les éléments de la liste qui précède\n              \n                  Show more\n              \n              \n                  Voir moins",
      "description": "Commission des Affaires étrangères et européennes, de la Défense, de la Coopération et de l'Immigration"
    },
    {
      "date": "23.04.2018",
      "type": "Nomination de rapporteur(s)\n\nRapporteur(s) : Monsieur Marc Angel",
      "description": "Marc Angel\n                      Commission des Affaires étrangères et européennes, de la Défense, de la Coopération et de l'Immigration"
    },
    {
      "date": "23.04.2018",
      "type": "- Désignation d'un rapporteur\n- Présentation du projet de loi",
      "description": "Commission des Affaires étrangères et européennes, de la Défense, de la Coopération et de l'Immigration",
      "link": "https://wdocs-pub.chd.lu/docs/exped/0009/088/18880.pdf"
    },
    {
      "date": "30.05.2018",
      "type": "Avis du Conseil d'État (29.5.2018)",
      "description": "Conseil d'État",
      "link": "https://wdocs-pub.chd.lu/docs/Dossiers_parlementaires/7260/20250513_Avis.pdf"
    },
    {
      "date": "04.06.2018",
      "type": "- Rapporteur : Monsieur Marc Angel\n - Analyse de l'avis du Conseil d'Etat",
      "description": "Commission des Affaires étrangères et européennes, de la Défense, de la Coopération et de l'Immigration",
      "link": "https://wdocs-pub.chd.lu/docs/exped/0010/123/21239.pdf"
    },
    {
      "date": "11.06.2018",
      "type": "Changement d'intitulé\n\nAncien intitulé : Projet de loi portant approbation de l'Accord de partenariat global et renforcé entre l'Union européenne et la Communauté européenne de l'énergie atomique et leurs États membres, d'une part, et la République d'Arménie, d'autre part, fait à Bruxelles, le 24 novembre 2017\n\nNouvel intitulé : Projet de loi portant approbation de l'Accord de partenariat global et renforcé entre l'Union européenne et la Communauté européenne de l'énergie atomique et leurs Etats membres, d'une part, et la République d'Arménie, d'autre part, fait à Bruxelles, le 24 novembre 2017\n                \n              \n            \n            \n              Bouton graphique servant à afficher ou cacher tous les éléments de la liste qui précède\n              \n                  Show more\n              \n              \n                  Voir moins",
      "description": ""
    },
    {
      "date": "11.06.2018",
      "type": "Rapport de commission(s) : Commission des Affaires étrangères et européennes, de la Défense, de la Coopération et de l'Immigration\n\nRapporteur(s) : Monsieur Marc Angel\n                \n              \n            \n            \n              Bouton graphique servant à afficher ou cacher tous les éléments de la liste qui précède\n              \n                  Show more\n              \n              \n                  Voir moins",
      "description": "Commission des Affaires étrangères et européennes, de la Défense, de la Coopération et de l'Immigration\n                      Marc Angel",
      "link": "https://wdocs-pub.chd.lu/docs/Dossiers_parlementaires/7260/20250514_RapportCommission.pdf"
    },
    {
      "date": "11.06.2018",
      "type": "- Rapporteur : Monsieur Marc Angel\n - Présentation et adoption d'un projet de rapport",
      "description": "Commission des Affaires étrangères et européennes, de la Défense, de la Coopération et de l'Immigration",
      "link": "https://wdocs-pub.chd.lu/docs/exped/0012/072/24721.pdf"
    },
    {
      "date": "27.06.2018",
      "type": "Premier vote constitutionnel (Vote Positif)\n\nEn séance publique n°44\n\nUne demande de dispense du second vote a été introduite\n                \n              \n            \n            \n              Bouton graphique servant à afficher ou cacher tous les éléments de la liste qui précède\n              \n                  Show more\n              \n              \n                  Voir moins",
      "description": "",
      "link": "https://wdocs-pub.chd.lu/docs/Dossiers_parlementaires/7260/20250515_BulletinVote.pdf"
    },
    {
      "date": "27.06.2018",
      "type": "7260 -  Projet de loi portant approbation de l'Accord de partenariat global et renforcé entre l'Union européenne et la Communauté européenne de l'énergie atomique et leurs Etats membres, d'une part, et la République d'Arménie, d'autre part, fait à Bruxelles, le 24 novembre 2017\n\n                \n              \n            \n            \n              Bouton graphique servant à afficher ou cacher tous les éléments de la liste qui précède\n              \n                  Show more\n              \n              \n                  Voir moins",
      "description": "",
      "link": "https://www.chd.lu/en/seance/2268?sequenceId=195587"
    },
    {
      "date": "05.07.2018",
      "type": "Dispense du second vote constitutionnel par le Conseil d'Etat (05-07-2018)\n\nEvacué par dispense du second vote (05-07-2018)\n                \n              \n            \n            \n              Bouton graphique servant à afficher ou cacher tous les éléments de la liste qui précède\n              \n                  Show more\n              \n              \n                  Voir moins",
      "description": "Conseil d'État",
      "link": "https://wdocs-pub.chd.lu/docs/Dossiers_parlementaires/7260/20250514_AccordDispenseSecondVote.pdf"
    },
    {
      "date": "23.07.2018",
      "type": "Publié au Mémorial A n°605 en page 1",
      "description": ""
    }
  ]
}
